<fox formatVersion="2" fileVersion="0">
  <entities>
    <entity class="DataSet" classVersion="0" classID="0xE8" addr="0xD5230A0" id="0x1EB92">
      <staticProperties>
        <property name="name" type="String" container="StaticArray" arraySize="1">
          <containerEntry hash="0xB8A0BF169F98"></containerEntry>
        </property>
        <property name="dataSet" type="EntityHandle" container="StaticArray" arraySize="1">
          <containerEntry>0x0</containerEntry>
        </property>
        <property name="dataList" type="EntityPtr" container="StringMap" arraySize="15">
          <containerEntry key="trap_CHK_bananaSouth">
            <data>0xD521580</data>
          </containerEntry>
          <containerEntry key="condition_0011">
            <data>0xD455480</data>
          </containerEntry>
          <containerEntry key="shape_0125">
            <data>0xD4504E0</data>
          </containerEntry>
          <containerEntry key="shape_0126">
            <data>0xD3DB6F0</data>
          </containerEntry>
          <containerEntry key="shape_0127">
            <data>0xD3DA110</data>
          </containerEntry>
          <containerEntry key="shape_0128">
            <data>0xD3D8270</data>
          </containerEntry>
          <containerEntry key="shape_0129">
            <data>0xD3D2700</data>
          </containerEntry>
          <containerEntry key="shape_0130">
            <data>0xD10CB80</data>
          </containerEntry>
          <containerEntry key="shape_0131">
            <data>0xD10B610</data>
          </containerEntry>
          <containerEntry key="shape_0132">
            <data>0xD109E00</data>
          </containerEntry>
          <containerEntry key="shape_0133">
            <data>0xD52DD70</data>
          </containerEntry>
          <containerEntry key="shape_0134">
            <data>0xD52DF30</data>
          </containerEntry>
          <containerEntry key="shape_0135">
            <data>0xD52E0F0</data>
          </containerEntry>
          <containerEntry key="shape_0136">
            <data>0xD52E2B0</data>
          </containerEntry>
          <containerEntry key="TexturePackLoadConditioner0000">
            <data>0xD455CD0</data>
          </containerEntry>
        </property>
      </staticProperties>
      <dynamicProperties></dynamicProperties>
    </entity>
    <entity class="GeoTrap" classVersion="2" classID="0x120" addr="0xD521580" id="0x18B0E1">
      <staticProperties>
        <property name="name" type="String" container="StaticArray" arraySize="1">
          <containerEntry>trap_CHK_bananaSouth</containerEntry>
        </property>
        <property name="dataSet" type="EntityHandle" container="StaticArray" arraySize="1">
          <containerEntry>0xD5230A0</containerEntry>
        </property>
        <property name="parent" type="EntityHandle" container="StaticArray" arraySize="1">
          <containerEntry>0x0</containerEntry>
        </property>
        <property name="transform" type="EntityPtr" container="StaticArray" arraySize="1">
          <containerEntry>0xD456520</containerEntry>
        </property>
        <property name="shearTransform" type="EntityPtr" container="StaticArray" arraySize="1">
          <containerEntry>0x0</containerEntry>
        </property>
        <property name="pivotTransform" type="EntityPtr" container="StaticArray" arraySize="1">
          <containerEntry>0x0</containerEntry>
        </property>
        <property name="children" type="EntityHandle" container="List" arraySize="13">
          <containerEntry>0xD455480</containerEntry>
          <containerEntry>0xD4504E0</containerEntry>
          <containerEntry>0xD3DB6F0</containerEntry>
          <containerEntry>0xD3DA110</containerEntry>
          <containerEntry>0xD3D8270</containerEntry>
          <containerEntry>0xD3D2700</containerEntry>
          <containerEntry>0xD10CB80</containerEntry>
          <containerEntry>0xD10B610</containerEntry>
          <containerEntry>0xD109E00</containerEntry>
          <containerEntry>0xD52DD70</containerEntry>
          <containerEntry>0xD52DF30</containerEntry>
          <containerEntry>0xD52E0F0</containerEntry>
          <containerEntry>0xD52E2B0</containerEntry>
        </property>
        <property name="flags" type="UInt32" container="StaticArray" arraySize="1">
          <containerEntry>7</containerEntry>
        </property>
        <property name="conditionArray" type="EntityLink" container="DynamicArray" arraySize="1">
          <containerEntry packagePathHash="0xB8A0BF169F98" archivePath="/Assets/tpp/level/location/mafr/block_mission2/outerBase/bananaSouth/trap/mafr_bananaSouth_trap_f01.fox2" nameInArchive="condition_0011">0xD455480</containerEntry>
        </property>
        <property name="enable" type="Bool" container="StaticArray" arraySize="1">
          <containerEntry>true</containerEntry>
        </property>
      </staticProperties>
      <dynamicProperties></dynamicProperties>
    </entity>
    <entity class="TransformEntity" classVersion="0" classID="0x50" addr="0xD456520" id="0x18B0E2">
      <staticProperties>
        <property name="owner" type="EntityHandle" container="StaticArray" arraySize="1">
          <containerEntry>0xD521580</containerEntry>
        </property>
        <property name="transform_scale" type="Vector3" container="StaticArray" arraySize="1">
          <containerEntry x="1" y="1" z="1" w="0"></containerEntry>
        </property>
        <property name="transform_rotation_quat" type="Quat" container="StaticArray" arraySize="1">
          <containerEntry x="0" y="0" z="0" w="1"></containerEntry>
        </property>
        <property name="transform_translation" type="Vector3" container="StaticArray" arraySize="1">
          <containerEntry x="234.96454" y="2.228561" z="-651.84595" w="0"></containerEntry>
        </property>
      </staticProperties>
      <dynamicProperties></dynamicProperties>
    </entity>
    <entity class="GeoModuleCondition" classVersion="0" classID="0x160" addr="0xD455480" id="0x18BBD2">
      <staticProperties>
        <property name="name" type="String" container="StaticArray" arraySize="1">
          <containerEntry>condition_0011</containerEntry>
        </property>
        <property name="dataSet" type="EntityHandle" container="StaticArray" arraySize="1">
          <containerEntry>0xD5230A0</containerEntry>
        </property>
        <property name="parent" type="EntityHandle" container="StaticArray" arraySize="1">
          <containerEntry>0xD521580</containerEntry>
        </property>
        <property name="transform" type="EntityPtr" container="StaticArray" arraySize="1">
          <containerEntry>0xD454B50</containerEntry>
        </property>
        <property name="shearTransform" type="EntityPtr" container="StaticArray" arraySize="1">
          <containerEntry>0x0</containerEntry>
        </property>
        <property name="pivotTransform" type="EntityPtr" container="StaticArray" arraySize="1">
          <containerEntry>0x0</containerEntry>
        </property>
        <property name="children" type="EntityHandle" container="List"></property>
        <property name="flags" type="UInt32" container="StaticArray" arraySize="1">
          <containerEntry>7</containerEntry>
        </property>
        <property name="trapCategory" type="String" container="StaticArray" arraySize="1">
          <containerEntry hash="0xB8A0BF169F98"></containerEntry>
        </property>
        <property name="trapPriority" type="UInt32" container="StaticArray" arraySize="1">
          <containerEntry>0</containerEntry>
        </property>
        <property name="enable" type="Bool" container="StaticArray" arraySize="1">
          <containerEntry>true</containerEntry>
        </property>
        <property name="isOnce" type="Bool" container="StaticArray" arraySize="1">
          <containerEntry>false</containerEntry>
        </property>
        <property name="isAndCheck" type="Bool" container="StaticArray" arraySize="1">
          <containerEntry>true</containerEntry>
        </property>
        <property name="checkFuncNames" type="String" container="DynamicArray" arraySize="1">
          <containerEntry>CanSaveAsCheckPoint</containerEntry>
        </property>
        <property name="execFuncNames" type="String" container="DynamicArray"></property>
        <property name="checkCallbackDataElements" type="EntityPtr" container="DynamicArray" arraySize="1">
          <containerEntry>0xD450DA0</containerEntry>
        </property>
        <property name="execCallbackDataElements" type="EntityPtr" container="DynamicArray"></property>
      </staticProperties>
      <dynamicProperties></dynamicProperties>
    </entity>
    <entity class="TransformEntity" classVersion="0" classID="0x50" addr="0xD454B50" id="0x18BBD3">
      <staticProperties>
        <property name="owner" type="EntityHandle" container="StaticArray" arraySize="1">
          <containerEntry>0xD455480</containerEntry>
        </property>
        <property name="transform_scale" type="Vector3" container="StaticArray" arraySize="1">
          <containerEntry x="10" y="38.83142" z="74.24477" w="0"></containerEntry>
        </property>
        <property name="transform_rotation_quat" type="Quat" container="StaticArray" arraySize="1">
          <containerEntry x="0" y="0.156329" z="0" w="0.987705"></containerEntry>
        </property>
        <property name="transform_translation" type="Vector3" container="StaticArray" arraySize="1">
          <containerEntry x="-0.1" y="-0.1" z="-0.1" w="0"></containerEntry>
        </property>
      </staticProperties>
      <dynamicProperties></dynamicProperties>
    </entity>
    <entity class="TppTrapCheckCanSaveAsCheckPointCallbackDataElement" classVersion="0" classID="0x20" addr="0xD450DA0" id="0x18C6C2">
      <staticProperties>
        <property name="owner" type="EntityHandle" container="StaticArray" arraySize="1">
          <containerEntry>0xD455480</containerEntry>
        </property>
        <property name="funcName" type="String" container="StaticArray" arraySize="1">
          <containerEntry>CanSaveAsCheckPoint</containerEntry>
        </property>
      </staticProperties>
      <dynamicProperties></dynamicProperties>
    </entity>
    <entity class="BoxShape" classVersion="0" classID="0x100" addr="0xD4504E0" id="0x18C6C3">
      <staticProperties>
        <property name="name" type="String" container="StaticArray" arraySize="1">
          <containerEntry>shape_0125</containerEntry>
        </property>
        <property name="dataSet" type="EntityHandle" container="StaticArray" arraySize="1">
          <containerEntry>0xD5230A0</containerEntry>
        </property>
        <property name="parent" type="EntityHandle" container="StaticArray" arraySize="1">
          <containerEntry>0xD521580</containerEntry>
        </property>
        <property name="transform" type="EntityPtr" container="StaticArray" arraySize="1">
          <containerEntry>0xD3DCAA0</containerEntry>
        </property>
        <property name="shearTransform" type="EntityPtr" container="StaticArray" arraySize="1">
          <containerEntry>0x0</containerEntry>
        </property>
        <property name="pivotTransform" type="EntityPtr" container="StaticArray" arraySize="1">
          <containerEntry>0x0</containerEntry>
        </property>
        <property name="children" type="EntityHandle" container="List"></property>
        <property name="flags" type="UInt32" container="StaticArray" arraySize="1">
          <containerEntry>7</containerEntry>
        </property>
      </staticProperties>
      <dynamicProperties></dynamicProperties>
    </entity>
    <entity class="TransformEntity" classVersion="0" classID="0x50" addr="0xD3DCAA0" id="0x18C6C4">
      <staticProperties>
        <property name="owner" type="EntityHandle" container="StaticArray" arraySize="1">
          <containerEntry>0xD4504E0</containerEntry>
        </property>
        <property name="transform_scale" type="Vector3" container="StaticArray" arraySize="1">
          <containerEntry x="10" y="38.83142" z="74.24477" w="0"></containerEntry>
        </property>
        <property name="transform_rotation_quat" type="Quat" container="StaticArray" arraySize="1">
          <containerEntry x="0" y="0.156329" z="0" w="0.987705"></containerEntry>
        </property>
        <property name="transform_translation" type="Vector3" container="StaticArray" arraySize="1">
          <containerEntry x="128.53406" y="3.542436" z="-49.884766" w="0"></containerEntry>
        </property>
      </staticProperties>
      <dynamicProperties></dynamicProperties>
    </entity>
    <entity class="BoxShape" classVersion="0" classID="0x100" addr="0xD3DB6F0" id="0x18D1B4">
      <staticProperties>
        <property name="name" type="String" container="StaticArray" arraySize="1">
          <containerEntry>shape_0126</containerEntry>
        </property>
        <property name="dataSet" type="EntityHandle" container="StaticArray" arraySize="1">
          <containerEntry>0xD5230A0</containerEntry>
        </property>
        <property name="parent" type="EntityHandle" container="StaticArray" arraySize="1">
          <containerEntry>0xD521580</containerEntry>
        </property>
        <property name="transform" type="EntityPtr" container="StaticArray" arraySize="1">
          <containerEntry>0xD3DB220</containerEntry>
        </property>
        <property name="shearTransform" type="EntityPtr" container="StaticArray" arraySize="1">
          <containerEntry>0x0</containerEntry>
        </property>
        <property name="pivotTransform" type="EntityPtr" container="StaticArray" arraySize="1">
          <containerEntry>0x0</containerEntry>
        </property>
        <property name="children" type="EntityHandle" container="List"></property>
        <property name="flags" type="UInt32" container="StaticArray" arraySize="1">
          <containerEntry>7</containerEntry>
        </property>
      </staticProperties>
      <dynamicProperties></dynamicProperties>
    </entity>
    <entity class="TransformEntity" classVersion="0" classID="0x50" addr="0xD3DB220" id="0x18D1B5">
      <staticProperties>
        <property name="owner" type="EntityHandle" container="StaticArray" arraySize="1">
          <containerEntry>0xD3DB6F0</containerEntry>
        </property>
        <property name="transform_scale" type="Vector3" container="StaticArray" arraySize="1">
          <containerEntry x="10" y="38.83142" z="74.46403" w="0"></containerEntry>
        </property>
        <property name="transform_rotation_quat" type="Quat" container="StaticArray" arraySize="1">
          <containerEntry x="0" y="0.453534" z="0" w="0.891239"></containerEntry>
        </property>
        <property name="transform_translation" type="Vector3" container="StaticArray" arraySize="1">
          <containerEntry x="87.02356" y="3.542436" z="-107.064514" w="0"></containerEntry>
        </property>
      </staticProperties>
      <dynamicProperties></dynamicProperties>
    </entity>
    <entity class="BoxShape" classVersion="0" classID="0x100" addr="0xD3DA110" id="0x18DCA5">
      <staticProperties>
        <property name="name" type="String" container="StaticArray" arraySize="1">
          <containerEntry>shape_0127</containerEntry>
        </property>
        <property name="dataSet" type="EntityHandle" container="StaticArray" arraySize="1">
          <containerEntry>0xD5230A0</containerEntry>
        </property>
        <property name="parent" type="EntityHandle" container="StaticArray" arraySize="1">
          <containerEntry>0xD521580</containerEntry>
        </property>
        <property name="transform" type="EntityPtr" container="StaticArray" arraySize="1">
          <containerEntry>0xD3D9AF0</containerEntry>
        </property>
        <property name="shearTransform" type="EntityPtr" container="StaticArray" arraySize="1">
          <containerEntry>0x0</containerEntry>
        </property>
        <property name="pivotTransform" type="EntityPtr" container="StaticArray" arraySize="1">
          <containerEntry>0x0</containerEntry>
        </property>
        <property name="children" type="EntityHandle" container="List"></property>
        <property name="flags" type="UInt32" container="StaticArray" arraySize="1">
          <containerEntry>7</containerEntry>
        </property>
      </staticProperties>
      <dynamicProperties></dynamicProperties>
    </entity>
    <entity class="TransformEntity" classVersion="0" classID="0x50" addr="0xD3D9AF0" id="0x18DCA6">
      <staticProperties>
        <property name="owner" type="EntityHandle" container="StaticArray" arraySize="1">
          <containerEntry>0xD3DA110</containerEntry>
        </property>
        <property name="transform_scale" type="Vector3" container="StaticArray" arraySize="1">
          <containerEntry x="10.00001" y="38.83142" z="74.97892" w="0"></containerEntry>
        </property>
        <property name="transform_rotation_quat" type="Quat" container="StaticArray" arraySize="1">
          <containerEntry x="0" y="0.705865" z="0" w="0.708346"></containerEntry>
        </property>
        <property name="transform_translation" type="Vector3" container="StaticArray" arraySize="1">
          <containerEntry x="19.656708" y="3.542436" z="-129.07434" w="0"></containerEntry>
        </property>
      </staticProperties>
      <dynamicProperties></dynamicProperties>
    </entity>
    <entity class="BoxShape" classVersion="0" classID="0x100" addr="0xD3D8270" id="0x18E796">
      <staticProperties>
        <property name="name" type="String" container="StaticArray" arraySize="1">
          <containerEntry>shape_0128</containerEntry>
        </property>
        <property name="dataSet" type="EntityHandle" container="StaticArray" arraySize="1">
          <containerEntry>0xD5230A0</containerEntry>
        </property>
        <property name="parent" type="EntityHandle" container="StaticArray" arraySize="1">
          <containerEntry>0xD521580</containerEntry>
        </property>
        <property name="transform" type="EntityPtr" container="StaticArray" arraySize="1">
          <containerEntry>0xD3D55D0</containerEntry>
        </property>
        <property name="shearTransform" type="EntityPtr" container="StaticArray" arraySize="1">
          <containerEntry>0x0</containerEntry>
        </property>
        <property name="pivotTransform" type="EntityPtr" container="StaticArray" arraySize="1">
          <containerEntry>0x0</containerEntry>
        </property>
        <property name="children" type="EntityHandle" container="List"></property>
        <property name="flags" type="UInt32" container="StaticArray" arraySize="1">
          <containerEntry>7</containerEntry>
        </property>
      </staticProperties>
      <dynamicProperties></dynamicProperties>
    </entity>
    <entity class="TransformEntity" classVersion="0" classID="0x50" addr="0xD3D55D0" id="0x18E797">
      <staticProperties>
        <property name="owner" type="EntityHandle" container="StaticArray" arraySize="1">
          <containerEntry>0xD3D8270</containerEntry>
        </property>
        <property name="transform_scale" type="Vector3" container="StaticArray" arraySize="1">
          <containerEntry x="10.000001" y="38.83142" z="74.29129" w="0"></containerEntry>
        </property>
        <property name="transform_rotation_quat" type="Quat" container="StaticArray" arraySize="1">
          <containerEntry x="0" y="0.89239" z="0" w="0.451265"></containerEntry>
        </property>
        <property name="transform_translation" type="Vector3" container="StaticArray" arraySize="1">
          <containerEntry x="-47.536804" y="3.542436" z="-107.21924" w="0"></containerEntry>
        </property>
      </staticProperties>
      <dynamicProperties></dynamicProperties>
    </entity>
    <entity class="BoxShape" classVersion="0" classID="0x100" addr="0xD3D2700" id="0x18F287">
      <staticProperties>
        <property name="name" type="String" container="StaticArray" arraySize="1">
          <containerEntry>shape_0129</containerEntry>
        </property>
        <property name="dataSet" type="EntityHandle" container="StaticArray" arraySize="1">
          <containerEntry>0xD5230A0</containerEntry>
        </property>
        <property name="parent" type="EntityHandle" container="StaticArray" arraySize="1">
          <containerEntry>0xD521580</containerEntry>
        </property>
        <property name="transform" type="EntityPtr" container="StaticArray" arraySize="1">
          <containerEntry>0xD3D20E0</containerEntry>
        </property>
        <property name="shearTransform" type="EntityPtr" container="StaticArray" arraySize="1">
          <containerEntry>0x0</containerEntry>
        </property>
        <property name="pivotTransform" type="EntityPtr" container="StaticArray" arraySize="1">
          <containerEntry>0x0</containerEntry>
        </property>
        <property name="children" type="EntityHandle" container="List"></property>
        <property name="flags" type="UInt32" container="StaticArray" arraySize="1">
          <containerEntry>7</containerEntry>
        </property>
      </staticProperties>
      <dynamicProperties></dynamicProperties>
    </entity>
    <entity class="TransformEntity" classVersion="0" classID="0x50" addr="0xD3D20E0" id="0x18F288">
      <staticProperties>
        <property name="owner" type="EntityHandle" container="StaticArray" arraySize="1">
          <containerEntry>0xD3D2700</containerEntry>
        </property>
        <property name="transform_scale" type="Vector3" container="StaticArray" arraySize="1">
          <containerEntry x="9.99999" y="38.83142" z="74.43845" w="0"></containerEntry>
        </property>
        <property name="transform_rotation_quat" type="Quat" container="StaticArray" arraySize="1">
          <containerEntry x="0" y="0.987549" z="0" w="0.15731"></containerEntry>
        </property>
        <property name="transform_translation" type="Vector3" container="StaticArray" arraySize="1">
          <containerEntry x="-88.96039" y="3.542436" z="-49.90515" w="0"></containerEntry>
        </property>
      </staticProperties>
      <dynamicProperties></dynamicProperties>
    </entity>
    <entity class="BoxShape" classVersion="0" classID="0x100" addr="0xD10CB80" id="0x18FD78">
      <staticProperties>
        <property name="name" type="String" container="StaticArray" arraySize="1">
          <containerEntry>shape_0130</containerEntry>
        </property>
        <property name="dataSet" type="EntityHandle" container="StaticArray" arraySize="1">
          <containerEntry>0xD5230A0</containerEntry>
        </property>
        <property name="parent" type="EntityHandle" container="StaticArray" arraySize="1">
          <containerEntry>0xD521580</containerEntry>
        </property>
        <property name="transform" type="EntityPtr" container="StaticArray" arraySize="1">
          <containerEntry>0xD10C560</containerEntry>
        </property>
        <property name="shearTransform" type="EntityPtr" container="StaticArray" arraySize="1">
          <containerEntry>0x0</containerEntry>
        </property>
        <property name="pivotTransform" type="EntityPtr" container="StaticArray" arraySize="1">
          <containerEntry>0x0</containerEntry>
        </property>
        <property name="children" type="EntityHandle" container="List"></property>
        <property name="flags" type="UInt32" container="StaticArray" arraySize="1">
          <containerEntry>7</containerEntry>
        </property>
      </staticProperties>
      <dynamicProperties></dynamicProperties>
    </entity>
    <entity class="TransformEntity" classVersion="0" classID="0x50" addr="0xD10C560" id="0x18FD79">
      <staticProperties>
        <property name="owner" type="EntityHandle" container="StaticArray" arraySize="1">
          <containerEntry>0xD10CB80</containerEntry>
        </property>
        <property name="transform_scale" type="Vector3" container="StaticArray" arraySize="1">
          <containerEntry x="10.000006" y="38.83142" z="39.094536" w="0"></containerEntry>
        </property>
        <property name="transform_rotation_quat" type="Quat" container="StaticArray" arraySize="1">
          <containerEntry x="0" y="0.990997" z="0" w="0.133885"></containerEntry>
        </property>
        <property name="transform_translation" type="Vector3" container="StaticArray" arraySize="1">
          <containerEntry x="-105.695435" y="3.542436" z="4.269226" w="0"></containerEntry>
        </property>
      </staticProperties>
      <dynamicProperties></dynamicProperties>
    </entity>
    <entity class="BoxShape" classVersion="0" classID="0x100" addr="0xD10B610" id="0x190869">
      <staticProperties>
        <property name="name" type="String" container="StaticArray" arraySize="1">
          <containerEntry>shape_0131</containerEntry>
        </property>
        <property name="dataSet" type="EntityHandle" container="StaticArray" arraySize="1">
          <containerEntry>0xD5230A0</containerEntry>
        </property>
        <property name="parent" type="EntityHandle" container="StaticArray" arraySize="1">
          <containerEntry>0xD521580</containerEntry>
        </property>
        <property name="transform" type="EntityPtr" container="StaticArray" arraySize="1">
          <containerEntry>0xD10B0D0</containerEntry>
        </property>
        <property name="shearTransform" type="EntityPtr" container="StaticArray" arraySize="1">
          <containerEntry>0x0</containerEntry>
        </property>
        <property name="pivotTransform" type="EntityPtr" container="StaticArray" arraySize="1">
          <containerEntry>0x0</containerEntry>
        </property>
        <property name="children" type="EntityHandle" container="List"></property>
        <property name="flags" type="UInt32" container="StaticArray" arraySize="1">
          <containerEntry>7</containerEntry>
        </property>
      </staticProperties>
      <dynamicProperties></dynamicProperties>
    </entity>
    <entity class="TransformEntity" classVersion="0" classID="0x50" addr="0xD10B0D0" id="0x19086A">
      <staticProperties>
        <property name="owner" type="EntityHandle" container="StaticArray" arraySize="1">
          <containerEntry>0xD10B610</containerEntry>
        </property>
        <property name="transform_scale" type="Vector3" container="StaticArray" arraySize="1">
          <containerEntry x="10.000009" y="38.83142" z="74.32902" w="0"></containerEntry>
        </property>
        <property name="transform_rotation_quat" type="Quat" container="StaticArray" arraySize="1">
          <containerEntry x="0" y="0.987509" z="0" w="-0.157564"></containerEntry>
        </property>
        <property name="transform_translation" type="Vector3" container="StaticArray" arraySize="1">
          <containerEntry x="-99.35365" y="3.542436" z="58.323242" w="0"></containerEntry>
        </property>
      </staticProperties>
      <dynamicProperties></dynamicProperties>
    </entity>
    <entity class="BoxShape" classVersion="0" classID="0x100" addr="0xD109E00" id="0x19135A">
      <staticProperties>
        <property name="name" type="String" container="StaticArray" arraySize="1">
          <containerEntry>shape_0132</containerEntry>
        </property>
        <property name="dataSet" type="EntityHandle" container="StaticArray" arraySize="1">
          <containerEntry>0xD5230A0</containerEntry>
        </property>
        <property name="parent" type="EntityHandle" container="StaticArray" arraySize="1">
          <containerEntry>0xD521580</containerEntry>
        </property>
        <property name="transform" type="EntityPtr" container="StaticArray" arraySize="1">
          <containerEntry>0xD109B60</containerEntry>
        </property>
        <property name="shearTransform" type="EntityPtr" container="StaticArray" arraySize="1">
          <containerEntry>0x0</containerEntry>
        </property>
        <property name="pivotTransform" type="EntityPtr" container="StaticArray" arraySize="1">
          <containerEntry>0x0</containerEntry>
        </property>
        <property name="children" type="EntityHandle" container="List"></property>
        <property name="flags" type="UInt32" container="StaticArray" arraySize="1">
          <containerEntry>7</containerEntry>
        </property>
      </staticProperties>
      <dynamicProperties></dynamicProperties>
    </entity>
    <entity class="TransformEntity" classVersion="0" classID="0x50" addr="0xD109B60" id="0x19135B">
      <staticProperties>
        <property name="owner" type="EntityHandle" container="StaticArray" arraySize="1">
          <containerEntry>0xD109E00</containerEntry>
        </property>
        <property name="transform_scale" type="Vector3" container="StaticArray" arraySize="1">
          <containerEntry x="9.99999" y="38.83142" z="74.4602" w="0"></containerEntry>
        </property>
        <property name="transform_rotation_quat" type="Quat" container="StaticArray" arraySize="1">
          <containerEntry x="0" y="0.891178" z="0" w="-0.453653"></containerEntry>
        </property>
        <property name="transform_translation" type="Vector3" container="StaticArray" arraySize="1">
          <containerEntry x="-57.787994" y="3.542436" z="115.38867" w="0"></containerEntry>
        </property>
      </staticProperties>
      <dynamicProperties></dynamicProperties>
    </entity>
    <entity class="BoxShape" classVersion="0" classID="0x100" addr="0xD52DD70" id="0x191E4B">
      <staticProperties>
        <property name="name" type="String" container="StaticArray" arraySize="1">
          <containerEntry>shape_0133</containerEntry>
        </property>
        <property name="dataSet" type="EntityHandle" container="StaticArray" arraySize="1">
          <containerEntry>0xD5230A0</containerEntry>
        </property>
        <property name="parent" type="EntityHandle" container="StaticArray" arraySize="1">
          <containerEntry>0xD521580</containerEntry>
        </property>
        <property name="transform" type="EntityPtr" container="StaticArray" arraySize="1">
          <containerEntry>0xD52DDE0</containerEntry>
        </property>
        <property name="shearTransform" type="EntityPtr" container="StaticArray" arraySize="1">
          <containerEntry>0x0</containerEntry>
        </property>
        <property name="pivotTransform" type="EntityPtr" container="StaticArray" arraySize="1">
          <containerEntry>0x0</containerEntry>
        </property>
        <property name="children" type="EntityHandle" container="List"></property>
        <property name="flags" type="UInt32" container="StaticArray" arraySize="1">
          <containerEntry>7</containerEntry>
        </property>
      </staticProperties>
      <dynamicProperties></dynamicProperties>
    </entity>
    <entity class="TransformEntity" classVersion="0" classID="0x50" addr="0xD52DDE0" id="0x191E4C">
      <staticProperties>
        <property name="owner" type="EntityHandle" container="StaticArray" arraySize="1">
          <containerEntry>0xD52DD70</containerEntry>
        </property>
        <property name="transform_scale" type="Vector3" container="StaticArray" arraySize="1">
          <containerEntry x="10.000006" y="38.83142" z="74.449036" w="0"></containerEntry>
        </property>
        <property name="transform_rotation_quat" type="Quat" container="StaticArray" arraySize="1">
          <containerEntry x="0" y="-0.707054" z="0" w="0.70716"></containerEntry>
        </property>
        <property name="transform_translation" type="Vector3" container="StaticArray" arraySize="1">
          <containerEntry x="9.428391" y="3.542436" z="137.24103" w="0"></containerEntry>
        </property>
      </staticProperties>
      <dynamicProperties></dynamicProperties>
    </entity>
    <entity class="BoxShape" classVersion="0" classID="0x100" addr="0xD52DF30" id="0x19293C">
      <staticProperties>
        <property name="name" type="String" container="StaticArray" arraySize="1">
          <containerEntry>shape_0134</containerEntry>
        </property>
        <property name="dataSet" type="EntityHandle" container="StaticArray" arraySize="1">
          <containerEntry>0xD5230A0</containerEntry>
        </property>
        <property name="parent" type="EntityHandle" container="StaticArray" arraySize="1">
          <containerEntry>0xD521580</containerEntry>
        </property>
        <property name="transform" type="EntityPtr" container="StaticArray" arraySize="1">
          <containerEntry>0xD52DFA0</containerEntry>
        </property>
        <property name="shearTransform" type="EntityPtr" container="StaticArray" arraySize="1">
          <containerEntry>0x0</containerEntry>
        </property>
        <property name="pivotTransform" type="EntityPtr" container="StaticArray" arraySize="1">
          <containerEntry>0x0</containerEntry>
        </property>
        <property name="children" type="EntityHandle" container="List"></property>
        <property name="flags" type="UInt32" container="StaticArray" arraySize="1">
          <containerEntry>7</containerEntry>
        </property>
      </staticProperties>
      <dynamicProperties></dynamicProperties>
    </entity>
    <entity class="TransformEntity" classVersion="0" classID="0x50" addr="0xD52DFA0" id="0x19293D">
      <staticProperties>
        <property name="owner" type="EntityHandle" container="StaticArray" arraySize="1">
          <containerEntry>0xD52DF30</containerEntry>
        </property>
        <property name="transform_scale" type="Vector3" container="StaticArray" arraySize="1">
          <containerEntry x="9.999998" y="38.83142" z="74.1923" w="0"></containerEntry>
        </property>
        <property name="transform_rotation_quat" type="Quat" container="StaticArray" arraySize="1">
          <containerEntry x="0" y="-0.454599" z="0" w="0.890696"></containerEntry>
        </property>
        <property name="transform_translation" type="Vector3" container="StaticArray" arraySize="1">
          <containerEntry x="76.64905" y="3.542436" z="115.471924" w="0"></containerEntry>
        </property>
      </staticProperties>
      <dynamicProperties></dynamicProperties>
    </entity>
    <entity class="BoxShape" classVersion="0" classID="0x100" addr="0xD52E0F0" id="0x19342D">
      <staticProperties>
        <property name="name" type="String" container="StaticArray" arraySize="1">
          <containerEntry>shape_0135</containerEntry>
        </property>
        <property name="dataSet" type="EntityHandle" container="StaticArray" arraySize="1">
          <containerEntry>0xD5230A0</containerEntry>
        </property>
        <property name="parent" type="EntityHandle" container="StaticArray" arraySize="1">
          <containerEntry>0xD521580</containerEntry>
        </property>
        <property name="transform" type="EntityPtr" container="StaticArray" arraySize="1">
          <containerEntry>0xD52E160</containerEntry>
        </property>
        <property name="shearTransform" type="EntityPtr" container="StaticArray" arraySize="1">
          <containerEntry>0x0</containerEntry>
        </property>
        <property name="pivotTransform" type="EntityPtr" container="StaticArray" arraySize="1">
          <containerEntry>0x0</containerEntry>
        </property>
        <property name="children" type="EntityHandle" container="List"></property>
        <property name="flags" type="UInt32" container="StaticArray" arraySize="1">
          <containerEntry>7</containerEntry>
        </property>
      </staticProperties>
      <dynamicProperties></dynamicProperties>
    </entity>
    <entity class="TransformEntity" classVersion="0" classID="0x50" addr="0xD52E160" id="0x19342E">
      <staticProperties>
        <property name="owner" type="EntityHandle" container="StaticArray" arraySize="1">
          <containerEntry>0xD52E0F0</containerEntry>
        </property>
        <property name="transform_scale" type="Vector3" container="StaticArray" arraySize="1">
          <containerEntry x="10" y="38.83142" z="74.58195" w="0"></containerEntry>
        </property>
        <property name="transform_rotation_quat" type="Quat" container="StaticArray" arraySize="1">
          <containerEntry x="0" y="-0.155792" z="0" w="0.98779"></containerEntry>
        </property>
        <property name="transform_translation" type="Vector3" container="StaticArray" arraySize="1">
          <containerEntry x="118.11911" y="3.542436" z="58.377686" w="0"></containerEntry>
        </property>
      </staticProperties>
      <dynamicProperties></dynamicProperties>
    </entity>
    <entity class="BoxShape" classVersion="0" classID="0x100" addr="0xD52E2B0" id="0x193F1E">
      <staticProperties>
        <property name="name" type="String" container="StaticArray" arraySize="1">
          <containerEntry>shape_0136</containerEntry>
        </property>
        <property name="dataSet" type="EntityHandle" container="StaticArray" arraySize="1">
          <containerEntry>0xD5230A0</containerEntry>
        </property>
        <property name="parent" type="EntityHandle" container="StaticArray" arraySize="1">
          <containerEntry>0xD521580</containerEntry>
        </property>
        <property name="transform" type="EntityPtr" container="StaticArray" arraySize="1">
          <containerEntry>0xD52E320</containerEntry>
        </property>
        <property name="shearTransform" type="EntityPtr" container="StaticArray" arraySize="1">
          <containerEntry>0x0</containerEntry>
        </property>
        <property name="pivotTransform" type="EntityPtr" container="StaticArray" arraySize="1">
          <containerEntry>0x0</containerEntry>
        </property>
        <property name="children" type="EntityHandle" container="List"></property>
        <property name="flags" type="UInt32" container="StaticArray" arraySize="1">
          <containerEntry>7</containerEntry>
        </property>
      </staticProperties>
      <dynamicProperties></dynamicProperties>
    </entity>
    <entity class="TransformEntity" classVersion="0" classID="0x50" addr="0xD52E320" id="0x193F1F">
      <staticProperties>
        <property name="owner" type="EntityHandle" container="StaticArray" arraySize="1">
          <containerEntry>0xD52E2B0</containerEntry>
        </property>
        <property name="transform_scale" type="Vector3" container="StaticArray" arraySize="1">
          <containerEntry x="10" y="38.83142" z="39.0887" w="0"></containerEntry>
        </property>
        <property name="transform_rotation_quat" type="Quat" container="StaticArray" arraySize="1">
          <containerEntry x="0" y="-0.134994" z="0" w="0.990846"></containerEntry>
        </property>
        <property name="transform_translation" type="Vector3" container="StaticArray" arraySize="1">
          <containerEntry x="134.77182" y="3.542436" z="4.231567" w="0"></containerEntry>
        </property>
      </staticProperties>
      <dynamicProperties></dynamicProperties>
    </entity>
    <entity class="TexturePackLoadConditioner" classVersion="0" classID="0x48" addr="0xD455CD0" id="0x0">
      <staticProperties>
        <property name="name" type="String" container="StaticArray" arraySize="1">
          <containerEntry>TexturePackLoadConditioner0000</containerEntry>
        </property>
        <property name="dataSet" type="EntityHandle" container="StaticArray" arraySize="1">
          <containerEntry>0xD5230A0</containerEntry>
        </property>
        <property name="texturePackPath" type="Path" container="StaticArray" arraySize="1">
          <containerEntry hash="0xB8A0BF169F98"></containerEntry>
        </property>
      </staticProperties>
      <dynamicProperties></dynamicProperties>
    </entity>
  </entities>
</fox>